fastdomaincheck_mcp_server/__init__.py
fastdomaincheck_mcp_server/checker.py
fastdomaincheck_mcp_server/server.py
fastdomaincheck_mcp_server-0.1.12.dist-info/licenses/LICENSE
fastdomaincheck_mcp_server-0.1.12.dist-info/METADATA
fastdomaincheck_mcp_server-0.1.12.dist-info/WHEEL
fastdomaincheck_mcp_server-0.1.12.dist-info/entry_points.txt
fastdomaincheck_mcp_server-0.1.12.dist-info/top_level.txt
fastdomaincheck_mcp_server-0.1.12.dist-info/RECORD
