Metadata-Version: 2.4
Name: fastdomaincheck-mcp-server
Version: 0.1.12
Summary: MCP Server for checking domain name availability using WHOIS and DNS via stdio.
Author-email: Bingal <bingalsky@gmail.com>
License-Expression: MIT
Project-URL: Homepage, https://fastdomaincheck.com/
Project-URL: Repository, https://github.com/bingal/fastdomaincheck-mcp-server-python
Keywords: mcp,domain,whois,dns,availability,check,stdio
Classifier: Development Status :: 3 - Alpha
Classifier: Intended Audience :: Developers
Classifier: Programming Language :: Python :: 3
Classifier: Programming Language :: Python :: 3.11
Classifier: Topic :: Internet :: Name Service (DNS)
Classifier: Topic :: Software Development :: Libraries :: Python Modules
Classifier: Operating System :: OS Independent
Requires-Python: >=3.11
License-File: LICENSE
Requires-Dist: mcp[cli]>=1.6.0
Dynamic: license-file
